temp_giphy_3_ti_client/__init__.py
temp_giphy_3_ti_client/api_client.py
temp_giphy_3_ti_client/api_response.py
temp_giphy_3_ti_client/configuration.py
temp_giphy_3_ti_client/exceptions.py
temp_giphy_3_ti_client/py.typed
temp_giphy_3_ti_client/rest.py
temp_giphy_3_ti_client/api/__init__.py
temp_giphy_3_ti_client/api/gifs_api.py
temp_giphy_3_ti_client/api/stickers_api.py
temp_giphy_3_ti_client/models/__init__.py
temp_giphy_3_ti_client/models/get_gifs_by_id200_response.py
temp_giphy_3_ti_client/models/gif.py
temp_giphy_3_ti_client/models/gif_images.py
temp_giphy_3_ti_client/models/gif_images_downsized.py
temp_giphy_3_ti_client/models/gif_images_downsized_large.py
temp_giphy_3_ti_client/models/gif_images_downsized_medium.py
temp_giphy_3_ti_client/models/gif_images_downsized_small.py
temp_giphy_3_ti_client/models/gif_images_downsized_still.py
temp_giphy_3_ti_client/models/gif_images_fixed_height.py
temp_giphy_3_ti_client/models/gif_images_fixed_height_downsampled.py
temp_giphy_3_ti_client/models/gif_images_fixed_height_small.py
temp_giphy_3_ti_client/models/gif_images_fixed_height_small_still.py
temp_giphy_3_ti_client/models/gif_images_fixed_height_still.py
temp_giphy_3_ti_client/models/gif_images_fixed_width.py
temp_giphy_3_ti_client/models/gif_images_fixed_width_downsampled.py
temp_giphy_3_ti_client/models/gif_images_fixed_width_small.py
temp_giphy_3_ti_client/models/gif_images_fixed_width_small_still.py
temp_giphy_3_ti_client/models/gif_images_fixed_width_still.py
temp_giphy_3_ti_client/models/gif_images_looping.py
temp_giphy_3_ti_client/models/gif_images_original.py
temp_giphy_3_ti_client/models/gif_images_original_still.py
temp_giphy_3_ti_client/models/gif_images_preview.py
temp_giphy_3_ti_client/models/gif_images_preview_gif.py
temp_giphy_3_ti_client/models/image.py
temp_giphy_3_ti_client/models/meta.py
temp_giphy_3_ti_client/models/pagination.py
temp_giphy_3_ti_client/models/random_gif200_response.py
temp_giphy_3_ti_client/models/user.py
temp_giphy_3_ti_client-1.0.0.dist-info/METADATA
temp_giphy_3_ti_client-1.0.0.dist-info/WHEEL
temp_giphy_3_ti_client-1.0.0.dist-info/top_level.txt
temp_giphy_3_ti_client-1.0.0.dist-info/RECORD
